rest_ai/__init__.py
rest_ai/exceptions.py
rest_ai/langchain/prompt_templates.py
rest_ai/rest_ai.py
rest_ai/utilities/__init__.py
rest_ai/utilities/config.py
rest_ai/utilities/openapi_utils.py
rest_ai/utilities/types.py
rest_ai-0.1.3.dist-info/METADATA
rest_ai-0.1.3.dist-info/WHEEL
rest_ai-0.1.3.dist-info/RECORD
